gradio_imagefeed/__init__.py
gradio_imagefeed/imagefeed.py
gradio_imagefeed/imagefeed.pyi
gradio_imagefeed/templates/component/__vite-browser-external-2447137e.js
gradio_imagefeed/templates/component/index.js
gradio_imagefeed/templates/component/style.css
gradio_imagefeed/templates/component/wrapper-6f348d45-f837cf34.js
gradio_imagefeed/templates/example/index.js
gradio_imagefeed/templates/example/style.css
gradio_imagefeed-0.0.1.dist-info/METADATA
gradio_imagefeed-0.0.1.dist-info/WHEEL
gradio_imagefeed-0.0.1.dist-info/RECORD
